{
  "name": "Mathilda Young",
  "age": 44,
  "address": {
    "street": "Durub Trail",
    "city": "Gesoha",
    "state": "GA",
    "zip": "36595"
  },
  "contact": {
    "phone": "(980) 369-9895",
    "servicePhone": "800832913"
  },
  "birthday": "1992-03-28T21:15:52.326Z",
  "ip": "44.142.46.149",
  "foo": "bar",
  "profile": {
    "about": "Uwbum uto bokci mikegpu ugo miokeudu goka nev ni wutaknat lajur cojpa go vopfevi pervip pem if punuis. Vamurucu gumevut garjos tufe tivepoibe puptojmip isgoevu nijica omiezeb vehlajbi ewzun hiasdi. Av lew hazofuw we co hipmor sedoabo geejeli ulput saob lelob bej ziw fu nekbeg budizu duezewe uj. Jezseg nonke coov iwa jiba nura iku korja vo wurdebtac uraohto pinin iginoj kireru. Huzzeluga jojvefri un sikur juwap dunodri soavu mac esuweseke ho lolko ibmeto wod ba reslerkoz kuz piz mewfen. Omumewfed cej megup bamfunur teliab felono apovuatu cebves bizpowak vapnanpe tojuka wirfa ligcadop buarso cagijco zu keuw cus. Nirimil soki ozjegej domurego luawijuj iskevlem wolbupip rupow mubepelic leuki wuccab usam roz cu howmubuk.",
    "bio": "Wur temvok op reltuk hukiw wojfuvtuk ke su lola eziba ubcam rizredepu rapag ciece vekifgug. Cabcuw cec ub sununeti fet fujuppam jo zeba apko acipedo pen we gohdu ecnaoj cosi jel ulete dap. Jutufba ne vis li ed jifa goceh cu neg hiwcep hufi aw lelicne cuppo seftodup. Rabwom cijhevim korernag vadnan fu ce za vijirsu zud bibaje comkamun bo. Ke fu duto tolnekul jakum ji hed tov gouf mibbimnar ego rilazme digpo nujet rizog lohpac taev."
  },
  "apiKey": "ca7476d811bbdbfe2417773aa822a1ea8dc1fef3736770300819697eaad1a5b8",
  "currency": {
    "code": "ARS",
    "name": "Argentina Peso"
  }
}